sageinspector/__init__.py
sageinspector/__main__.py
sageinspector/_env.py
sageinspector/_version.py
sageinspector/cli/__init__.py
sageinspector/cli/_base.py
sageinspector/cli/describe.py
sageinspector/cli/logs.py
sageinspector/cli/open.py
sageinspector/cli/scaffold.py
sageinspector/lib/__init__.py
sageinspector/lib/arn.py
sageinspector/lib/logs.py
sageinspector/lib/resource.py
sageinspector/util/__init__.py
sageinspector/util/aws_config.py
sageinspector/util/settings.py
sageinspector-0.0.2.dist-info/LICENSE
sageinspector-0.0.2.dist-info/METADATA
sageinspector-0.0.2.dist-info/NOTICE
sageinspector-0.0.2.dist-info/WHEEL
sageinspector-0.0.2.dist-info/entry_points.txt
sageinspector-0.0.2.dist-info/top_level.txt
sageinspector-0.0.2.dist-info/RECORD
