Metadata-Version: 2.1
Name: sageinspector
Version: 0.0.2
Summary: Tool to easily inspect Amazon SageMaker resources.
Home-page: https://github.com/awslabs/sage-inspector
License: Apache-2.0
Platform: UNKNOWN
Requires-Python: >=3.7
Requires-Dist: boto3
Requires-Dist: click (>=8.0)
Requires-Dist: pydantic
Requires-Dist: toolz
